Metadata-Version: 1.1
Name: biogridpy
Version: 0.1.1
Summary: Python client for the BioGRID REST API webservice
Home-page: https://github.com/arvkevi/biogridpy
Author: Kevin Arvai
Author-email: arvkevi@gmail.com
License: MIT
Download-URL: https://github.com/arvkevi/biogridpy/tarball/0.1.1
Keywords: genetics,genomics,interaction,bioinformatics
Platform: UNKNOWN
Classifier: Programming Language :: Python
Classifier: Programming Language :: Python :: 2.7
Classifier: Programming Language :: Python :: 3
Classifier: Intended Audience :: Science/Research
Classifier: Topic :: Scientific/Engineering :: Bio-Informatics
